{
    "sourceFile": "content/css/main.css",
    "activeCommit": 0,
    "commits": [
        {
            "activePatchIndex": 1,
            "patches": [
                {
                    "date": 1659158177907,
                    "content": "Index: \n===================================================================\n--- \n+++ \n"
                },
                {
                    "date": 1659158185620,
                    "content": "Index: \n===================================================================\n--- \n+++ \n@@ -0,0 +1,1018 @@\n+.wrapper {\r\n+    background-color: #eaeaea9a;\r\n+    width: 100%;\r\n+    max-width: 1365px;\r\n+    margin: 0 auto;\r\n+}\r\n+\r\n+.width100 {\r\n+    width: 100%;\r\n+    max-width: 1365px;\r\n+    background-color: #f5f5f5;\r\n+}\r\n+\r\n+.header {\r\n+    height: 102px;\r\n+    display: flex;\r\n+    justify-content: space-between;\r\n+    font-size: 1.4rem;\r\n+    align-items: center;\r\n+    padding: 75px 0;\r\n+}\r\n+\r\n+.avatar {\r\n+    width: 25px;\r\n+    height: 25px;\r\n+    border-radius: 50%;\r\n+    object-fit: cover;\r\n+}\r\n+\r\n+.avatar_comment {\r\n+    width: 60px;\r\n+    height: 60px;\r\n+    object-fit: cover;\r\n+    border-radius: 50%;\r\n+}\r\n+\r\n+.header__logo {\r\n+    width: 25%;\r\n+}\r\n+\r\n+.header__logo a {\r\n+    color: var(--primary) !important;\r\n+    font-size: 3.4rem;\r\n+    font-weight: bold;\r\n+}\r\n+\r\n+.header__search {\r\n+    width: 50%;\r\n+    position: relative;\r\n+}\r\n+\r\n+.header__input {\r\n+    width: 90%;\r\n+    border: 1px solid var(--primary);\r\n+    padding: 6px 10px;\r\n+    border-radius: 5px;\r\n+}\r\n+\r\n+.header__btn {\r\n+    width: 8%;\r\n+    position: absolute;\r\n+    top: 0;\r\n+    right: 10%;\r\n+    padding: 7px 10px;\r\n+    background-color: var(--primary);\r\n+    border-top-right-radius: 5px;\r\n+    border-bottom-right-radius: 5px;\r\n+    color: white;\r\n+}\r\n+\r\n+.header__btn:hover {\r\n+    opacity: 0.8;\r\n+}\r\n+\r\n+.header__user {\r\n+    cursor: pointer;\r\n+    position: relative;\r\n+}\r\n+\r\n+.header__user:hover .user__dropDown {\r\n+    display: block;\r\n+}\r\n+\r\n+.user__dropDown {\r\n+    position: absolute;\r\n+    bottom: -310%;\r\n+    right: 0;\r\n+    width: 243px;\r\n+    background-color: white;\r\n+    z-index: 1000;\r\n+    box-shadow: 1px 1px 7px rgba(0, 0, 0, 0.3);\r\n+    animation: fade-grow 0.4s ease;\r\n+    transform-origin: 80% top;\r\n+    display: none;\r\n+}\r\n+\r\n+.user__dropDown.margin {\r\n+    position: absolute;\r\n+    bottom: -370%;\r\n+    right: 0;\r\n+    width: 243px;\r\n+    background-color: white;\r\n+    z-index: 1000;\r\n+    box-shadow: 1px 1px 7px rgba(0, 0, 0, 0.3);\r\n+    animation: fade-grow 0.4s ease;\r\n+    transform-origin: 80% top;\r\n+    display: none;\r\n+}\r\n+\r\n+.user__dropDown-items:hover {\r\n+    background-color: #eaeaea67;\r\n+}\r\n+\r\n+.user__dropDown-items-link {\r\n+    color: var(--dark);\r\n+}\r\n+\r\n+.countNotify {\r\n+    background-color: var(--primary);\r\n+    border-radius: 30%;\r\n+    padding: 0px 8px;\r\n+    font-size: 1rem;\r\n+    color: white;\r\n+}\r\n+\r\n+.user__dropDown-items-link:hover {\r\n+    color: var(--dark);\r\n+}\r\n+\r\n+.user__dropDown:before {\r\n+    position: absolute;\r\n+    content: \"\";\r\n+    top: 0;\r\n+    right: 5%;\r\n+    transform: translateY(-90%);\r\n+    border-width: 14px 20px;\r\n+    border-style: solid;\r\n+    border-color: transparent transparent white transparent;\r\n+    z-index: 100;\r\n+}\r\n+\r\n+.user__dropDown::after {\r\n+    position: absolute;\r\n+    content: \"\";\r\n+    top: -44%;\r\n+    right: 0;\r\n+    width: 46%;\r\n+    height: 65px;\r\n+    z-index: -10;\r\n+}\r\n+\r\n+a.header__link:hover {\r\n+    opacity: 0.8;\r\n+}\r\n+\r\n+.header__cart {\r\n+    position: relative;\r\n+}\r\n+\r\n+.icon__header {\r\n+    font-size: 2.2rem;\r\n+}\r\n+\r\n+.cart {\r\n+    position: relative;\r\n+}\r\n+\r\n+.cart__items {\r\n+    position: absolute;\r\n+    top: -50%;\r\n+    right: -50%;\r\n+    background-color: var(--primary);\r\n+    width: 17px;\r\n+    height: 17px;\r\n+    border-radius: 50%;\r\n+    display: flex;\r\n+    justify-content: center;\r\n+    align-items: center;\r\n+    color: white;\r\n+    font-size: 1.1rem;\r\n+    font-weight: bold;\r\n+}\r\n+\r\n+\r\n+/* end header */\r\n+\r\n+.nav {\r\n+    align-items: center;\r\n+    font-size: 1.4rem;\r\n+    /* text-transform: uppercase; */\r\n+    font-weight: bold;\r\n+    /* background-color: rgba(255, 255, 255, 0.876); */\r\n+    background-color: white;\r\n+    line-height: 1px;\r\n+}\r\n+\r\n+.nav__category-title {\r\n+    text-transform: uppercase;\r\n+}\r\n+\r\n+.nav__link {\r\n+    padding: 14px 32px;\r\n+    color: var(--dark);\r\n+    text-transform: uppercase;\r\n+}\r\n+\r\n+.nav__link:hover {\r\n+    color: var(--primary);\r\n+}\r\n+\r\n+.nav__category-ul {\r\n+    position: absolute;\r\n+    top: 100%;\r\n+    left: 0;\r\n+    width: 100%;\r\n+    z-index: 100;\r\n+    background-color: white;\r\n+    /* border: 1px solid #eaeaea83; */\r\n+    box-shadow: 0 0 10px rgba(0, 0, 0, 0.2);\r\n+    display: none;\r\n+}\r\n+\r\n+.nav__category {\r\n+    /* width: 273px; */\r\n+    width: 23%;\r\n+    background-color: var(--foreign);\r\n+    padding: 14px 10px;\r\n+    position: relative;\r\n+}\r\n+\r\n+.nav__category:hover .nav__category-ul {\r\n+    display: block;\r\n+}\r\n+\r\n+.icon__category {\r\n+    padding-right: 9px;\r\n+}\r\n+\r\n+\r\n+/* end nav */\r\n+\r\n+.main {\r\n+    padding: 14px 0;\r\n+}\r\n+\r\n+.main__category {\r\n+    background-color: white;\r\n+    font-size: 1.4rem;\r\n+    flex: 0 0 23%;\r\n+    max-width: 23%;\r\n+    margin-top: -14px;\r\n+    padding: 0;\r\n+    border: 1px solid #eaeaea83;\r\n+    border-bottom-left-radius: 5px;\r\n+}\r\n+\r\n+.icon__cate {\r\n+    padding-right: 4px;\r\n+}\r\n+\r\n+.main__category-items {\r\n+    padding: 12px 8px;\r\n+    border-bottom: 1px solid #eaeaea83;\r\n+}\r\n+\r\n+.main__category-link:last-child .main__category-items {\r\n+    border: none;\r\n+}\r\n+\r\n+.main__category-items:hover {\r\n+    background-color: #eaeaea67;\r\n+}\r\n+\r\n+.main__category-link {\r\n+    color: var(--dark);\r\n+    font-weight: 500;\r\n+}\r\n+\r\n+.main__category-link:hover {\r\n+    color: var(--dark);\r\n+}\r\n+\r\n+.main__silde {\r\n+    padding-right: 0;\r\n+    flex: 0 0 77%;\r\n+    max-width: 77%;\r\n+    overflow: hidden;\r\n+    height: 300px;\r\n+    position: relative;\r\n+    border-bottom-right-radius: 5px;\r\n+    border-top-right-radius: 5px;\r\n+}\r\n+\r\n+.owl-slidebanner .owl-nav {\r\n+    width: 100%;\r\n+    position: absolute;\r\n+    top: 50%;\r\n+    transform: translateY(-50%);\r\n+}\r\n+\r\n+.owl-slidebanner .owl-nav .owl-prev {\r\n+    position: absolute;\r\n+    font-size: 1.8rem;\r\n+    padding: 3px 18px;\r\n+    opacity: 0.7;\r\n+    transform: translateY(-50%);\r\n+    left: 0;\r\n+}\r\n+\r\n+.owl-slidebanner .owl-nav .owl-next {\r\n+    position: absolute;\r\n+    font-size: 1.8rem;\r\n+    padding: 3px 18px;\r\n+    opacity: 0.7;\r\n+    right: 0;\r\n+    transform: translateY(-50%);\r\n+}\r\n+\r\n+.main__silde img {\r\n+    width: 100%;\r\n+    height: 300px;\r\n+}\r\n+\r\n+\r\n+/* quicklinks */\r\n+\r\n+.quicklinks {\r\n+    background-color: white;\r\n+    display: flex;\r\n+    justify-content: space-between;\r\n+    align-items: center;\r\n+    margin: 20px 0;\r\n+    padding: 20px;\r\n+    border-radius: 5px;\r\n+}\r\n+\r\n+\r\n+/* animation rung lắc */\r\n+\r\n+@keyframes shaking {\r\n+    10% {\r\n+        transform: translateX(3px) rotate(2deg);\r\n+    }\r\n+    20% {\r\n+        transform: translateX(-3px) rotate(-2deg);\r\n+    }\r\n+    30% {\r\n+        transform: translateX(3px) rotate(2deg);\r\n+    }\r\n+    40% {\r\n+        transform: translateX(-3px) rotate(-2deg);\r\n+    }\r\n+    50% {\r\n+        transform: translateX(2px) rotate(1deg);\r\n+    }\r\n+    60% {\r\n+        transform: translateX(-2px) rotate(-1deg);\r\n+    }\r\n+    70% {\r\n+        transform: translateX(2px) rotate(1deg);\r\n+    }\r\n+    80% {\r\n+        transform: translateX(-2px) rotate(-1deg);\r\n+    }\r\n+    90% {\r\n+        transform: translateX(1px) rotate(0);\r\n+    }\r\n+    100% {\r\n+        transform: translateX(-1px) rotate(0);\r\n+    }\r\n+}\r\n+\r\n+.quicklinks svg {\r\n+    width: 5rem;\r\n+    height: 5rem;\r\n+    padding: 10px;\r\n+    background-color: primary;\r\n+    border-radius: 5px;\r\n+    fill: white;\r\n+}\r\n+\r\n+.quicklinks svg:hover {\r\n+    animation: shaking 0.7s linear;\r\n+}\r\n+\r\n+.quicklinks a {\r\n+    width: 20%;\r\n+    color: var(--dark);\r\n+    font-weight: 500;\r\n+}\r\n+\r\n+.quicklinks a p {\r\n+    font-size: 1.4rem;\r\n+    padding-top: 8px;\r\n+    margin: 0;\r\n+}\r\n+\r\n+.quicklinks-code svg {\r\n+    background-color: #0c9ff3;\r\n+}\r\n+\r\n+.quicklinks-freeship svg {\r\n+    background-color: #ff7d7d;\r\n+}\r\n+\r\n+.quicklinks-marketing svg {\r\n+    background-color: #ffa200;\r\n+}\r\n+\r\n+.quicklinks-newmember svg {\r\n+    background-color: #0867b4;\r\n+}\r\n+\r\n+.quicklinks-coin svg {\r\n+    background-color: #02b9d4;\r\n+}\r\n+\r\n+.quicklinks-pay svg {\r\n+    background-color: #7373ef;\r\n+}\r\n+\r\n+\r\n+/* end quicklinks */\r\n+\r\n+.flash__sale {\r\n+    position: relative;\r\n+    background-color: white;\r\n+    border-radius: 5px;\r\n+    padding-bottom: 10px;\r\n+}\r\n+\r\n+.flash__sale-top {\r\n+    display: flex;\r\n+    justify-content: space-between;\r\n+    align-items: center;\r\n+    padding: 20px;\r\n+}\r\n+\r\n+.flash__sale-top-text {\r\n+    display: flex;\r\n+    align-items: center;\r\n+    justify-content: space-between;\r\n+    width: 50%;\r\n+}\r\n+\r\n+.icon__flash-sale {\r\n+    animation: setflash__sale 0.5s infinite;\r\n+    color: var(--orange);\r\n+}\r\n+\r\n+.flash__sale-heading {\r\n+    font-size: 2.2rem;\r\n+    font-weight: bold;\r\n+    text-transform: uppercase;\r\n+    color: var(--orange);\r\n+}\r\n+\r\n+@keyframes setflash__sale {\r\n+    from {\r\n+        opacity: 1;\r\n+        transform: scale(1);\r\n+    }\r\n+    to {\r\n+        opacity: 0.8;\r\n+        transform: scale(1.6);\r\n+    }\r\n+}\r\n+\r\n+.flash__sale-countdown {\r\n+    display: flex;\r\n+    justify-content: center;\r\n+    flex: 1;\r\n+    align-items: center;\r\n+}\r\n+\r\n+.item__count {\r\n+    background-color: var(--primary);\r\n+    width: 36px;\r\n+    height: 34px;\r\n+    border-radius: 5px;\r\n+    display: flex;\r\n+    align-items: center;\r\n+    justify-content: center;\r\n+    font-weight: 600;\r\n+    font-size: 1.4rem;\r\n+    color: rgba(255, 255, 255, 0.952);\r\n+    line-height: 3.4rem;\r\n+    margin: 0 3%;\r\n+}\r\n+\r\n+.separa {\r\n+    font-size: 1.5rem;\r\n+    color: var(--primary);\r\n+}\r\n+\r\n+.owl-nav.disabled {\r\n+    display: block !important;\r\n+}\r\n+\r\n+.owl-flash__sale .owl-nav {\r\n+    position: absolute;\r\n+    top: -16.4%;\r\n+    right: 0;\r\n+}\r\n+\r\n+.owl-flash__sale .owl-nav .owl-next {\r\n+    font-size: 1.8rem;\r\n+    padding: 3px 15px;\r\n+}\r\n+\r\n+.owl-flash__sale .owl-nav .owl-prev {\r\n+    font-size: 1.8rem;\r\n+    padding: 3px 15px;\r\n+}\r\n+\r\n+.product-sale {\r\n+    border: 1px solid #eaeaea;\r\n+    background: white;\r\n+    border-radius: 5px;\r\n+    padding: 0 3%;\r\n+    min-height: 410px;\r\n+    position: relative;\r\n+}\r\n+\r\n+.product-sale-lable {\r\n+    position: absolute;\r\n+    top: 0;\r\n+    left: 0;\r\n+    width: 40px;\r\n+    height: 36px;\r\n+    background-color: #ffa200;\r\n+    display: flex;\r\n+    border-top-left-radius: 5px;\r\n+    align-items: center;\r\n+    justify-content: center;\r\n+    font-size: 1.4rem;\r\n+    color: white;\r\n+}\r\n+\r\n+.product-sale-lable:before {\r\n+    position: absolute;\r\n+    content: \"\";\r\n+    left: 0;\r\n+    bottom: -4px;\r\n+    border-width: 0 20px 4px;\r\n+    border-style: solid;\r\n+    border-color: #ffa200 #ffa200 transparent #ffa200;\r\n+}\r\n+\r\n+.product-sale__title {\r\n+    font-weight: 400;\r\n+    line-height: 2rem;\r\n+    height: 40px;\r\n+    overflow: hidden;\r\n+    /* white-space:nowrap;\r\n+  text-overflow: ellipsis; */\r\n+    display: -webkit-box;\r\n+    -webkit-box-orient: vertical;\r\n+    -webkit-line-clamp: 2;\r\n+    color: var(--dark);\r\n+}\r\n+\r\n+.product-sale__img {\r\n+    /* padding: 10% 0;\r\n+  height: 193px; */\r\n+    padding-top: 70% !important;\r\n+    background-repeat: no-repeat;\r\n+    background-size: contain;\r\n+    background-position: center;\r\n+}\r\n+\r\n+.icon__vote {\r\n+    color: var(--orange);\r\n+}\r\n+\r\n+.product-sale-price {\r\n+    display: flex;\r\n+    align-items: center;\r\n+    color: var(--dark);\r\n+    justify-content: space-between;\r\n+}\r\n+\r\n+.product-sale__new-price {\r\n+    font-size: 1.5rem;\r\n+    color: var(--dark);\r\n+    font-weight: bold;\r\n+}\r\n+\r\n+.product-sale-old-price {\r\n+    color: var(--secondary);\r\n+    color: var(--dark);\r\n+    font-size: 1.3rem;\r\n+}\r\n+\r\n+.product-sale-sold {\r\n+    width: 100%;\r\n+    height: 7px;\r\n+    background-color: #dc354644;\r\n+    border-radius: 7px;\r\n+    position: relative;\r\n+}\r\n+\r\n+.product-sale-sold-count {\r\n+    position: absolute;\r\n+    height: 100%;\r\n+    background-color: var(--primary);\r\n+    border-radius: 7px;\r\n+}\r\n+\r\n+.product-sale-sold-total {\r\n+    color: var(--dark);\r\n+    font-size: 1.4rem;\r\n+}\r\n+\r\n+.product-sale:hover .new__product-items-img-slider__button-bar-btn {\r\n+    opacity: 1;\r\n+    margin-left: 0;\r\n+}\r\n+\r\n+.new__product-items-img-slider__button-bar {\r\n+    position: absolute;\r\n+    top: 50%;\r\n+    left: 2%;\r\n+    transform: translateY(-50%);\r\n+}\r\n+\r\n+.new__product-items-img-slider__button-bar-btn {\r\n+    width: 30px;\r\n+    height: 30px;\r\n+    background-color: #666;\r\n+    margin: 5px 0;\r\n+    border-radius: 5px;\r\n+    color: var(--white);\r\n+    font-size: 1.3rem;\r\n+    display: flex;\r\n+    transition: all 0.4s;\r\n+    margin-left: -20px;\r\n+    opacity: 0;\r\n+    cursor: pointer;\r\n+}\r\n+\r\n+.new__product-items-img-slider__button-bar-btn:hover {\r\n+    background-color: var(--primary);\r\n+    color: white;\r\n+}\r\n+\r\n+.new__product-items-img-slider__button-bar-btn:is(:nth-child(2), :nth-child(3)) {\r\n+    transition-delay: 0.1s;\r\n+}\r\n+\r\n+.new__product-items-img-slider__button-bar-btn:nth-child(3) {\r\n+    transition-delay: 0.1s;\r\n+}\r\n+\r\n+.new__product-items-img-slider__button-bar-btn i {\r\n+    margin: auto;\r\n+}\r\n+\r\n+.new__product-items-img-slider__button-bar-btn-add__cart:hover .new__product-items-img-slider__button-bar-btn-add__cart-text {\r\n+    display: flex;\r\n+}\r\n+\r\n+.new__product-items-img-slider__button-bar-btn-add__cart {\r\n+    position: relative;\r\n+}\r\n+\r\n+.new__product-items-img-slider__button-bar-btn-add__cart-text {\r\n+    position: absolute;\r\n+    left: 90%;\r\n+    bottom: 0;\r\n+    height: inherit;\r\n+    width: 100px;\r\n+    background-color: inherit;\r\n+    display: flex;\r\n+    justify-content: center;\r\n+    align-items: center;\r\n+    display: none;\r\n+    transition: 0.1s;\r\n+    transform-origin: left 50%;\r\n+    border-top-right-radius: 5px;\r\n+    border-bottom-right-radius: 5px;\r\n+    animation: slideBarAddCart ease-in 0.3s;\r\n+}\r\n+\r\n+@keyframes slideBarAddCart {\r\n+    from {\r\n+        transform: scale(0);\r\n+    }\r\n+    to {\r\n+        transform: scale(1);\r\n+    }\r\n+}\r\n+\r\n+\r\n+/* end flash__sale */\r\n+\r\n+\r\n+/* end main */\r\n+\r\n+.footer {}\r\n+\r\n+\r\n+/* footer */\r\n+\r\n+.footer {\r\n+    background-color: white;\r\n+}\r\n+\r\n+.footer__info {\r\n+    display: flex;\r\n+    justify-content: space-between;\r\n+    padding: 3% 0;\r\n+}\r\n+\r\n+.footer__contact {\r\n+    flex: 2;\r\n+}\r\n+\r\n+.footer__local {\r\n+    flex: 1;\r\n+}\r\n+\r\n+.footer__service {\r\n+    flex: 1;\r\n+}\r\n+\r\n+.footer__tag {\r\n+    flex: 2;\r\n+}\r\n+\r\n+.footer__heading {\r\n+    font-size: 1.6rem;\r\n+    color: var(--dark);\r\n+    padding-bottom: 10px;\r\n+}\r\n+\r\n+.footer__contact-items,\r\n+.footer__local-items,\r\n+.footer__service-items {\r\n+    font-size: 1.3rem;\r\n+}\r\n+\r\n+.footer__info a {\r\n+    color: #222;\r\n+}\r\n+\r\n+.footer__contact-items {\r\n+    padding: 10px 0;\r\n+}\r\n+\r\n+.footer__local-items {\r\n+    padding: 10px 0;\r\n+    transition: 0.3s;\r\n+}\r\n+\r\n+.footer__service-items {\r\n+    padding: 10px 0;\r\n+    transition: 0.3s;\r\n+}\r\n+\r\n+.footer__local-items:hover,\r\n+.footer__service-items:hover {\r\n+    margin-left: 13px;\r\n+    list-style: disc;\r\n+    color: var(--primary);\r\n+}\r\n+\r\n+.footer__local-items:hover a,\r\n+.footer__service-items:hover a {\r\n+    color: var(--primary);\r\n+}\r\n+\r\n+.footer__contact-items i {\r\n+    padding-right: 8px;\r\n+}\r\n+\r\n+.footer__tag-items {\r\n+    display: inline-block;\r\n+    padding: 12px;\r\n+    background-color: #f5f5f5;\r\n+    font-size: 1.1rem;\r\n+    margin: 5px 5px 5px 0;\r\n+    transition: 0.3s ease;\r\n+    border-radius: 5px;\r\n+    position: relative;\r\n+}\r\n+\r\n+.footer__tag-items::before {\r\n+    position: absolute;\r\n+    content: \"\";\r\n+    width: 0;\r\n+    height: 100%;\r\n+    bottom: 0;\r\n+    background-color: var(--primary);\r\n+    left: 0;\r\n+    transition: 0.4s;\r\n+    z-index: 0;\r\n+    border-radius: 5px;\r\n+}\r\n+\r\n+.footer__tag-items a {\r\n+    z-index: 10;\r\n+    position: relative;\r\n+    transition: 0.3s;\r\n+}\r\n+\r\n+.footer__tag-items:hover.footer__tag-items a {\r\n+    color: white;\r\n+}\r\n+\r\n+.footer__tag-items:hover.footer__tag-items::before {\r\n+    width: 100%;\r\n+}\r\n+\r\n+\r\n+/* .footer__social-form */\r\n+\r\n+.footer__social-form {\r\n+    background-color: #f5f5f5;\r\n+    padding: 2.4% 5%;\r\n+    display: flex;\r\n+    align-items: center;\r\n+    background-image: url(\"https://images.unsplash.com/photo-1626271812535-249679371de6?ixid=MnwxMjA3fDB8MHxwaG90by1wYWdlfHx8fGVufDB8fHx8&ixlib=rb-1.2.1&auto=format&fit=crop&w=718&q=80\");\r\n+    background-size: cover;\r\n+    background-repeat: no-repeat;\r\n+    background-attachment: fixed;\r\n+}\r\n+\r\n+.footer__socical {\r\n+    display: flex;\r\n+    flex: 1;\r\n+    padding-right: 2%;\r\n+}\r\n+\r\n+.footer__socical-link {\r\n+    background-color: white;\r\n+    width: 45px;\r\n+    height: 45px;\r\n+    border-radius: 50px;\r\n+    color: var(--dark);\r\n+    transition: 0.3s ease-out;\r\n+    display: inline-block;\r\n+    float: left;\r\n+    overflow: hidden;\r\n+    margin: 0 5px;\r\n+}\r\n+\r\n+.footer__socical-link+.footer__socical-link {\r\n+    margin-left: 10px;\r\n+}\r\n+\r\n+.footer__socical-btn {\r\n+    line-height: 45px;\r\n+    display: inline-block;\r\n+    width: 45px;\r\n+    border-radius: 50%;\r\n+    text-align: center;\r\n+    height: 45px;\r\n+    transition: 0.3s ease-out;\r\n+}\r\n+\r\n+.footer__socical-btn i {\r\n+    line-height: 45px;\r\n+    font-size: 2rem;\r\n+    transition: 0.3s ease-out;\r\n+}\r\n+\r\n+.footer__socical-link:nth-child(1) .footer__socical-btn i {\r\n+    color: #1877f2;\r\n+}\r\n+\r\n+.footer__socical-link:nth-child(2) .footer__socical-btn i {\r\n+    color: #1da1f2;\r\n+}\r\n+\r\n+.footer__socical-link:nth-child(3) .footer__socical-btn i {\r\n+    color: #ff3300;\r\n+}\r\n+\r\n+.footer__socical-link:nth-child(4) .footer__socical-btn i {\r\n+    color: #e4405f;\r\n+}\r\n+\r\n+.footer__socical-link:nth-child(5) .footer__socical-btn i {\r\n+    color: #cd201f;\r\n+}\r\n+\r\n+.footer__socical-link span {\r\n+    font-size: 1.3rem;\r\n+    font-weight: 900;\r\n+    line-height: 45px;\r\n+    text-align: center;\r\n+    margin-left: 5px;\r\n+}\r\n+\r\n+.footer__socical-link:hover {\r\n+    width: 140px;\r\n+}\r\n+\r\n+.footer__socical-link:nth-child(1):hover .footer__socical-btn {\r\n+    background-color: #1877f2;\r\n+}\r\n+\r\n+.footer__socical-link:nth-child(2):hover .footer__socical-btn {\r\n+    background-color: #1da1f2;\r\n+}\r\n+\r\n+.footer__socical-link:nth-child(3):hover .footer__socical-btn {\r\n+    background-color: #ff3300;\r\n+}\r\n+\r\n+.footer__socical-link:nth-child(4):hover .footer__socical-btn {\r\n+    background-color: #e4405f;\r\n+}\r\n+\r\n+.footer__socical-link:nth-child(5):hover .footer__socical-btn {\r\n+    background-color: #cd201f;\r\n+}\r\n+\r\n+.footer__socical-link:hover .footer__socical-btn i {\r\n+    color: white;\r\n+}\r\n+\r\n+.footer__socical-link:nth-child(1):hover span {\r\n+    color: #1877f2;\r\n+}\r\n+\r\n+.footer__socical-link:nth-child(2):hover span {\r\n+    color: #1da1f2;\r\n+}\r\n+\r\n+.footer__socical-link:nth-child(3):hover span {\r\n+    color: #ff3300;\r\n+}\r\n+\r\n+.footer__socical-link:nth-child(4):hover span {\r\n+    color: #e4405f;\r\n+}\r\n+\r\n+.footer__socical-link:nth-child(5):hover span {\r\n+    color: #cd201f;\r\n+}\r\n+\r\n+.footer__form {\r\n+    flex: 2;\r\n+    display: flex;\r\n+    justify-content: space-around;\r\n+    align-items: center;\r\n+    position: relative;\r\n+}\r\n+\r\n+.footer__form-heading {\r\n+    font-size: 2rem;\r\n+    color: white;\r\n+}\r\n+\r\n+.footer__form-heading span {\r\n+    font-size: 3rem;\r\n+    color: var(--primary);\r\n+    font-weight: bold;\r\n+}\r\n+\r\n+.footer__form-input {\r\n+    width: 30%;\r\n+    font-size: 1.6rem;\r\n+    height: 38px;\r\n+    padding: 10px 0;\r\n+    border-radius: 40px;\r\n+    outline: none;\r\n+    border: 1px solid #efefef;\r\n+    padding-left: 20px;\r\n+    box-shadow: 0 0 5px rgba(0, 0, 0, 0.1);\r\n+}\r\n+\r\n+::-webkit-input-placeholder {\r\n+    font-size: 1.2rem;\r\n+}\r\n+\r\n+.footer__form-btn {\r\n+    border: none;\r\n+    font-size: 2rem;\r\n+    cursor: pointer;\r\n+    position: absolute;\r\n+    transition: 0.4s;\r\n+    top: 8%;\r\n+    right: 4.2%;\r\n+    background-color: rgba(255, 110, 64, 0.01);\r\n+}\r\n+\r\n+.footer__form-btn:hover {\r\n+    transform: rotate(360deg);\r\n+}\r\n+\r\n+\r\n+/* footer__copyright */\r\n+\r\n+.footer__copyright {\r\n+    display: flex;\r\n+    justify-content: space-between;\r\n+    padding: 2% 5%;\r\n+    align-items: center;\r\n+}\r\n+\r\n+.footer__copyright-left {\r\n+    font-size: 1.4rem;\r\n+    color: var(--dark);\r\n+}\r\n+\r\n+.footer__copyright-img:hover {\r\n+    opacity: 0.8;\r\n+    cursor: pointer;\r\n+}\r\n+\r\n+\r\n+/* end footer */\r\n+\r\n+\r\n+/* new_product */\n\\ No newline at end of file\n"
                }
            ],
            "date": 1659158177907,
            "name": "Commit-0",
            "content": ""
        }
    ]
}